{
  "slug": "gmo-btob",
  "name": "GMOペイメントゲートウェイ株式会社",
  "brandName": "GMO BtoB早払い",
  "description": "GMOペイメントゲートウェイ株式会社が提供する法人間取引の売掛債権を早期資金化するファクタリングサービス。請求書買取（手数料1%〜10%）に加え、注文書の段階でも買取に応じる点が特徴的。2回目以降は最短2営業日で入金され、東証プライム上場企業が運営する高い信頼性も魅力。",
  "affiliateUrl": "https://www.gmo-pg.com/lpc/hayabarai/",
  "factoringType": "2社間",
  "feeRange": {
    "min": 1,
    "max": 12
  },
  "minAmount": 1000000,
  "maxAmount": 1000000000,
  "speedDays": 2,
  "onlineComplete": true,
  "soleProprietorOk": true,
  "weekendPayment": false,
  "features": [
    "東証プライム上場企業運営",
    "注文書買取対応",
    "手数料1%〜",
    "オンライン完結",
    "法人専用"
  ],
  "pros": [
    "対応が迅速",
    "審査が柔軟",
    "全国対応"
  ],
  "cons": [
    "知名度がやや低い",
    "手数料は個別査定"
  ],
  "targetIndustries": [
    "建設業",
    "運送業",
    "製造業",
    "IT・Web",
    "サービス業"
  ],
  "overallRating": 4.3,
  "rankPosition": 29,
  "requiredDocuments": [
    "請求書",
    "基本契約書",
    "発注書",
    "決算書"
  ],
  "address": "東京都渋谷区道玄坂1-2-3 渋谷フクラス",
  "faq": [
    {
      "question": "GMO BtoB早払いとはどのようなサービスですか？",
      "answer": "GMOペイメントゲートウェイ株式会社が提供するファクタリングサービスです。東証プライム上場のGMOグループの信頼性があります。"
    },
    {
      "question": "手数料はいくらですか？",
      "answer": "手数料は1%〜10%です。GMOグループの資金力を活かした競争力のある料金設定です。"
    },
    {
      "question": "個人事業主でも利用できますか？",
      "answer": "主に法人向けのサービスですが、個人事業主も利用できるケースがあります。詳細はお問い合わせください。"
    },
    {
      "question": "GMOペイメントゲートウェイとは？",
      "answer": "東証プライム上場のGMOインターネットグループの決済代行会社です。国内有数の決済処理実績を持ち、安定した運営基盤があります。"
    },
    {
      "question": "オンラインで完結できますか？",
      "answer": "はい、オンラインでの手続きに対応しています。"
    }
  ],
  "feeSimulation": [
    {
      "amount": 1000000,
      "feeMin": 10000,
      "feeMax": 100000,
      "handMin": 900000,
      "handMax": 990000
    },
    {
      "amount": 5000000,
      "feeMin": 50000,
      "feeMax": 500000,
      "handMin": 4500000,
      "handMax": 4950000
    },
    {
      "amount": 10000000,
      "feeMin": 100000,
      "feeMax": 1000000,
      "handMin": 9000000,
      "handMax": 9900000
    }
  ],
  "comparisons": [
    {
      "competitor": "OLTA",
      "competitorSlug": "olta",
      "points": [
        "GMO BtoB早払いは東証プライム上場企業が直接運営",
        "OLTAはAI審査で手数料2〜9%、GMOは1〜10%",
        "両社ともオンライン完結型"
      ]
    },
    {
      "competitor": "セゾンインボイス",
      "competitorSlug": "saison-invoice",
      "points": [
        "GMOは決済大手、セゾンは信販大手のグループ",
        "両社とも手数料1%〜の低コスト",
        "GMOはIT企業ならではのテクノロジー活用"
      ]
    }
  ],
  "detailSections": {
    "merits": [
      {
        "title": "手数料1〜12%と業界でも低水準",
        "body": "GMO BtoB早払いの手数料は1〜12%に設定されています。特に下限1%は業界でも低い水準で、売掛先の信用力が高い場合やリピート利用時にはさらに有利な条件が期待できます。手数料を抑えたい方にとって魅力的な選択肢です。"
      },
      {
        "title": "最短2日で計画的な資金調達が可能",
        "body": "GMO BtoB早払いは最短2日での入金に対応しています。即日入金ほどのスピードではないものの、計画的に資金調達を進めたい場合には十分な対応速度です。その分、丁寧な審査と適正な手数料設定が期待できます。"
      },
      {
        "title": "最大10億円までの大口案件に対応",
        "body": "買取上限が10億円と高額に設定されているため、建設業の大型工事代金や製造業の大口取引など、まとまった金額の売掛金にも対応可能です。大口の資金調達を検討している企業にとって心強い選択肢です。"
      },
      {
        "title": "取引先に知られない2社間ファクタリング",
        "body": "GMO BtoB早払いは2社間ファクタリング専門のため、取引先への通知は一切行われません。「ファクタリングの利用を取引先に知られたくない」という方にとって、安心して利用できるサービスです。取引先との関係を維持しながら資金調達が可能です。"
      },
      {
        "title": "オンライン完結で来店不要",
        "body": "GMO BtoB早払いは申し込みから契約・入金まで全てオンラインで完結します。来店の必要がないため、全国どこからでも利用でき、忙しい経営者でも空いた時間に手続きが可能です。スマートフォンからの申し込みにも対応しています。"
      }
    ],
    "demerits": [
      {
        "title": "知名度が大手と比較するとやや低い",
        "body": "GMO BtoB早払いは業界大手と比較すると知名度がやや低いため、情報を集めにくいと感じる方もいるかもしれません。ただし、知名度と実際のサービス品質は必ずしも比例しないため、手数料や対応スピード、口コミなどを総合的に判断することが重要です。"
      },
      {
        "title": "手数料は個別査定で事前に確定しない",
        "body": "GMO BtoB早払いの手数料は売掛先の信用力や取引内容によって個別に決まります。申し込み前に正確な手数料がわからないため、一律料金のサービスと比べると事前のコスト計算がしづらい面があります。ただし、無料見積もりを利用すれば契約前に確認できます。"
      },
      {
        "title": "土日祝日の審査・入金には非対応",
        "body": "GMO BtoB早払いは土日祝日の審査・入金には対応していません。週末に急な資金需要が発生した場合は翌営業日まで待つ必要があります。土日にも対応が必要な場合は、週末対応のファクタリング会社と併用することも検討しましょう。"
      }
    ],
    "recommended": [
      "個人事業主・フリーランスで資金繰りを改善したい方",
      "取引先に知られずに資金調達したい方",
      "手数料を安く抑えたい方",
      "来店不要でオンラインで手続きを完結させたい方",
      "大口の売掛金を早期に資金化したい企業"
    ],
    "flow": [
      {
        "step": "Webから無料相談・申し込み",
        "detail": "GMO BtoB早払いの公式サイトから申し込みフォームに必要事項を入力します。売掛金の内容や希望金額を伝えましょう。"
      },
      {
        "step": "必要書類をアップロード",
        "detail": "請求書・基本契約書・発注書・決算書をオンラインで提出します。"
      },
      {
        "step": "審査・買取条件の提示",
        "detail": "書類をもとに審査が行われ、手数料と買取金額が提示されます。条件に納得できない場合はキャンセルも可能です。"
      },
      {
        "step": "契約・入金",
        "detail": "オンラインで契約を締結後、最短2日で指定口座に入金されます。"
      }
    ]
  }
}