{
  "slug": "localworks-payment",
  "name": "株式会社ローカルワークス",
  "brandName": "ローカルワークスペイメント",
  "description": "品川区に拠点を置き建設業界に強い2社間・3社間ファクタリング。工事代金や請負代金の早期現金化に対応し、手数料3〜15%で最短即日入金。個人事業主や一人親方も利用可能で、地域密着型ならではの丁寧なサポートが特徴。",
  "affiliateUrl": "https://localworks-payment.jp/",
  "factoringType": "2社間・3社間",
  "feeRange": {
    "min": 3,
    "max": 15
  },
  "minAmount": 300000,
  "maxAmount": 50000000,
  "speedDays": 1,
  "onlineComplete": true,
  "soleProprietorOk": true,
  "weekendPayment": false,
  "features": [
    "地域密着",
    "建設業界に強い",
    "即日入金",
    "個人事業主OK",
    "柔軟な審査"
  ],
  "pros": [
    "対応が迅速",
    "審査が柔軟",
    "全国対応"
  ],
  "cons": [
    "知名度がやや低い",
    "手数料は個別査定"
  ],
  "targetIndustries": [
    "建設業",
    "運送業",
    "製造業",
    "IT・Web",
    "サービス業"
  ],
  "overallRating": 3,
  "rankPosition": 233,
  "requiredDocuments": ["請求書", "通帳コピー", "本人確認書類"],
  "address": "東京都品川区西五反田7-1-10"
}
