{
  "slug": "shikin-quick",
  "name": "株式会社MIRIZE",
  "brandName": "資金調達QUICK",
  "description": "MIRIZEが運営する2社間ファクタリング「資金調達QUICK」。手数料1〜15%、最短10分で振込の圧倒的スピード。累計申込10万件超・満足度98%の実績を持ち、土日祝も営業で急な資金需要に即対応します。",
  "affiliateUrl": "https://shikin-quick.com/",
  "factoringType": "2社間",
  "feeRange": {
    "min": 1,
    "max": 15
  },
  "minAmount": 10000,
  "maxAmount": 50000000,
  "speedDays": 1,
  "onlineComplete": true,
  "soleProprietorOk": true,
  "weekendPayment": false,
  "features": [
    "最短10分入金",
    "手数料1%〜",
    "累計10万件超",
    "オンライン完結",
    "個人事業主OK"
  ],
  "pros": [
    "対応が迅速",
    "審査が柔軟",
    "全国対応"
  ],
  "cons": [
    "知名度がやや低い",
    "手数料は個別査定"
  ],
  "targetIndustries": [
    "建設業",
    "運送業",
    "製造業",
    "IT・Web",
    "サービス業"
  ],
  "overallRating": 3.5,
  "rankPosition": 210,
  "requiredDocuments": [
    "身分証明書",
    "口座入出金履歴",
    "請求書"
  ],
  "address": "東京都港区三田3-4-3 RIPL9",
  "faq": [
    {
      "question": "資金調達QUICKの手数料はいくらですか？",
      "answer": "資金調達QUICKの手数料は1〜15%の範囲で、売掛先の信用力や取引金額に応じて個別に査定されます。売掛先が上場企業や官公庁の場合、低い手数料が適用される傾向があります。見積もりは無料ですので、まずはお気軽にお問い合わせください。"
    },
    {
      "question": "資金調達QUICKは個人事業主やフリーランスでも利用できますか？",
      "answer": "はい、資金調達QUICKは個人事業主・フリーランスの方も利用可能です。1万円からの少額にも対応しているため、小規模な売掛金でも気軽に利用できます。"
    },
    {
      "question": "資金調達QUICKの入金スピードはどのくらいですか？",
      "answer": "資金調達QUICKは最短即日での入金に対応しています。午前中に申し込みと必要書類の提出を完了すれば、当日中に入金される可能性が高いです。オンラインで手続きが完結するため、来店の必要はありません。"
    },
    {
      "question": "資金調達QUICKを利用すると取引先に知られますか？",
      "answer": "資金調達QUICKは2社間ファクタリングのため、取引先への通知は一切行われません。利用者と資金調達QUICKの2者間で取引が完結するため、取引先との関係に影響なく資金調達が可能です。"
    },
    {
      "question": "資金調達QUICKの利用に必要な書類は何ですか？",
      "answer": "資金調達QUICKの利用に必要な書類は、身分証明書、口座入出金履歴、請求書です。必要書類が少ないため、手続きの負担が軽いのが特徴です。詳しくは公式サイトまたは無料相談でご確認ください。"
    }
  ],
  "feeSimulation": [
    {
      "amount": 1000000,
      "feeMin": 10000,
      "feeMax": 150000,
      "handMin": 850000,
      "handMax": 990000
    },
    {
      "amount": 5000000,
      "feeMin": 50000,
      "feeMax": 750000,
      "handMin": 4250000,
      "handMax": 4950000
    },
    {
      "amount": 10000000,
      "feeMin": 100000,
      "feeMax": 1500000,
      "handMin": 8500000,
      "handMax": 9900000
    }
  ],
  "comparisons": [
    {
      "competitor": "資金調達ペイ",
      "competitorSlug": "shikin-pay",
      "points": [
        "資金調達QUICKの手数料は1〜15%で、資金調達ペイ（3〜15%）より低め",
        "両社とも即日入金に対応"
      ]
    },
    {
      "competitor": "VISTIA",
      "competitorSlug": "vistia",
      "points": [
        "資金調達QUICKの手数料は1〜15%で、VISTIA（3〜15%）より低め",
        "両社とも即日入金に対応"
      ]
    }
  ],
  "detailSections": {
    "merits": [
      {
        "title": "手数料1〜15%と業界でも低水準",
        "body": "資金調達QUICKの手数料は1〜15%に設定されています。特に下限1%は業界でも低い水準で、売掛先の信用力が高い場合やリピート利用時にはさらに有利な条件が期待できます。手数料を抑えたい方にとって魅力的な選択肢です。"
      },
      {
        "title": "最短即日の入金スピードで急な資金需要に対応",
        "body": "申し込みから最短即日で入金が完了するため、急な支払いや予定外の出費にもスピーディーに対応できます。オンラインで手続きが完結するため、時間や場所を選ばずに申し込みが可能です。"
      },
      {
        "title": "1万円からの少額にも対応",
        "body": "買取金額は1万円から対応しているため、フリーランスや個人事業主の小口の売掛金でも利用しやすいのが強みです。「少額だから断られるかも」という心配をせずに申し込めるのは、特に小規模事業者にとって大きなメリットです。"
      },
      {
        "title": "取引先に知られない2社間ファクタリング",
        "body": "資金調達QUICKは2社間ファクタリング専門のため、取引先への通知は一切行われません。「ファクタリングの利用を取引先に知られたくない」という方にとって、安心して利用できるサービスです。取引先との関係を維持しながら資金調達が可能です。"
      },
      {
        "title": "オンライン完結で来店不要",
        "body": "資金調達QUICKは申し込みから契約・入金まで全てオンラインで完結します。来店の必要がないため、全国どこからでも利用でき、忙しい経営者でも空いた時間に手続きが可能です。スマートフォンからの申し込みにも対応しています。"
      }
    ],
    "demerits": [
      {
        "title": "知名度が大手と比較するとやや低い",
        "body": "資金調達QUICKは業界大手と比較すると知名度がやや低いため、情報を集めにくいと感じる方もいるかもしれません。ただし、知名度と実際のサービス品質は必ずしも比例しないため、手数料や対応スピード、口コミなどを総合的に判断することが重要です。"
      },
      {
        "title": "手数料は個別査定で事前に確定しない",
        "body": "資金調達QUICKの手数料は売掛先の信用力や取引内容によって個別に決まります。申し込み前に正確な手数料がわからないため、一律料金のサービスと比べると事前のコスト計算がしづらい面があります。ただし、無料見積もりを利用すれば契約前に確認できます。"
      },
      {
        "title": "土日祝日の審査・入金には非対応",
        "body": "資金調達QUICKは土日祝日の審査・入金には対応していません。週末に急な資金需要が発生した場合は翌営業日まで待つ必要があります。土日にも対応が必要な場合は、週末対応のファクタリング会社と併用することも検討しましょう。"
      }
    ],
    "recommended": [
      "急な支払いに対応するため即日入金が必要な方",
      "個人事業主・フリーランスで資金繰りを改善したい方",
      "取引先に知られずに資金調達したい方",
      "手数料を安く抑えたい方",
      "来店不要でオンラインで手続きを完結させたい方"
    ],
    "flow": [
      {
        "step": "Webから無料相談・申し込み",
        "detail": "資金調達QUICKの公式サイトから申し込みフォームに必要事項を入力します。売掛金の内容や希望金額を伝えましょう。"
      },
      {
        "step": "必要書類をアップロード",
        "detail": "身分証明書・口座入出金履歴・請求書をオンラインで提出します。"
      },
      {
        "step": "審査・買取条件の提示",
        "detail": "書類をもとに審査が行われ、手数料と買取金額が提示されます。条件に納得できない場合はキャンセルも可能です。"
      },
      {
        "step": "契約・入金",
        "detail": "オンラインで契約を締結後、最短即日で指定口座に入金されます。"
      }
    ]
  }
}