{
  "slug": "trapay",
  "name": "株式会社トラストゲートウェイ",
  "brandName": "トラペイ",
  "description": "",
  "affiliateUrl": "https://trapay.jp/",
  "factoringType": "2社間",
  "feeRange": {
    "min": 2,
    "max": 12
  },
  "minAmount": 100000,
  "maxAmount": 50000000,
  "speedDays": 1,
  "onlineComplete": true,
  "soleProprietorOk": false,
  "weekendPayment": false,
  "features": [
    "オンライン完結",
    "業界最安水準の手数料",
    "必要書類が少ない",
    "全国対応",
    "法人・個人対応"
  ],
  "pros": [
    "対応が迅速",
    "審査が柔軟",
    "全国対応"
  ],
  "cons": [
    "知名度がやや低い",
    "手数料は個別査定"
  ],
  "targetIndustries": [
    "建設業",
    "運送業",
    "製造業",
    "IT・Web",
    "サービス業"
  ],
  "overallRating": 3.5,
  "rankPosition": 213
}